.gitignore
ChangeLog
LICENSE
MANIFEST.in
README
buildout.cfg
djangodash_fixture.json
refresh_buildout.sh
run.sh
setup.py
shell.sh
example/setup.py
example/src/antichaos_example/__init__.py
example/src/antichaos_example/admin.py
example/src/antichaos_example/models.py
example/src/antichaos_example/settings-ng.py
example/src/antichaos_example/settings.py
example/src/antichaos_example/urls.py
example/src/antichaos_example/management/__init__.py
example/src/antichaos_example/management/commands/__init__.py
example/src/antichaos_example/management/commands/upload_bookmarks.py
example/src/antichaos_example/media/css/common.css
src/django_antichaos/__init__.py
src/django_antichaos/models.py
src/django_antichaos/tests.py
src/django_antichaos/urls.py
src/django_antichaos/utils.py
src/django_antichaos/views.py
src/django_antichaos.egg-info/PKG-INFO
src/django_antichaos.egg-info/SOURCES.txt
src/django_antichaos.egg-info/dependency_links.txt
src/django_antichaos.egg-info/not-zip-safe
src/django_antichaos.egg-info/top_level.txt
src/django_antichaos/management/__init__.py
src/django_antichaos/management/commands/__init__.py
src/django_antichaos/management/commands/antichaos_process_rules.py
src/django_antichaos/media/antichaos.css
src/django_antichaos/media/antichaos.js
src/django_antichaos/media/effects.core.js
src/django_antichaos/media/effects.explode.js
src/django_antichaos/media/jquery.js
src/django_antichaos/media/simpletip.js
src/django_antichaos/media/ui.core.js
src/django_antichaos/media/ui.draggable.js
src/django_antichaos/media/ui.droppable.js
src/django_antichaos/templates/admin/tagging/app_index.html
src/django_antichaos/templates/antichaos/tag_cloud.html
src/django_antichaos/templates/antichaos/tag_cloud_list.html
src/django_antichaos/templates/antichaos/tag_preview.html
src/django_antichaos/templatetags/__init__.py
src/django_antichaos/templatetags/antichaos.py