Metadata-Version: 1.0
Name: django-antichaos
Version: 0.2.0
Summary: Django application for easy tag manipulation.It's addon to django-tagging or django-taggin-ng applications.
Home-page: http://github.com/svetlyak40wt/django-antichaos/
Author: Alexander Artemenko
Author-email: svetlyak.40wt@gmail.com
License: New BSD License
Keywords: django apps tagging tags jquery javascript
Platform: UNKNOWN
Classifier: Development Status :: 2 - Pre-Alpha
Classifier: Environment :: Plugins
Classifier: Framework :: Django
Classifier: Intended Audience :: Developers
Classifier: License :: OSI Approved :: BSD License
Classifier: Programming Language :: Python
Classifier: Programming Language :: JavaScript
Classifier: Topic :: Software Development :: Libraries :: Python Modules
